payme_uz/__init__.py
payme_uz/requests.py
payme_uz/cards/__init__.py
payme_uz/cards/cards.py
payme_uz/receipts/__init__.py
payme_uz/receipts/receipts.py
aiopay-1.0.4.dist-info/METADATA
aiopay-1.0.4.dist-info/WHEEL
aiopay-1.0.4.dist-info/top_level.txt
aiopay-1.0.4.dist-info/RECORD
