Metadata-Version: 2.1
Name: aiopay
Version: 1.0.4
Summary: Payme API uchun Asinxron kutubxona!!!
Home-page: https://github.com/bultakov/aiopay
Author: Ibrohim Bultakov
Author-email: bii23.uz@gmail.com
License: MIT
Keywords: paycom,paymeuz,pypi,python,paycomuz,aiopay
Classifier: Framework :: AsyncIO
Classifier: License :: OSI Approved :: MIT License
Classifier: Programming Language :: Python :: 3.7
Classifier: Programming Language :: Python :: 3.8
Classifier: Programming Language :: Python :: 3.9
Classifier: Programming Language :: Python :: 3.10
Requires-Python: >=3.7
Requires-Dist: aiohttp (<3.9.0,>=3.8.0)
